CHANGELOG.md
LICENSE
utr/__init__.py
utr/ccp.py
utr/classes.py
utr/cli/__init__.py
utr/cli/cli.py
utr/cli/player/__init__.py
utr/cli/player/commands.py
utr/cli/results/__init__.py
utr/cli/results/commands.py
utr/cli/score/__init__.py
utr/cli/score/commands.py
utr/club.py
utr/main.py
utr/settings.py
utr/util.py
utr-1.1.1.dist-info/entry_points.txt
utr-1.1.1.dist-info/LICENSE
utr-1.1.1.dist-info/WHEEL
utr-1.1.1.dist-info/METADATA
utr-1.1.1.dist-info/RECORD
