Metadata-Version: 2.1
Name: utr
Version: 1.1.1
Summary: A python library to interact with UTR API
Home-page: https://github.com/userlerueda/utr
License: GPL-3.0-or-later
Author: Luis Rueda
Author-email: userlerueda@gmail.com
Requires-Python: >=3.9,<4.0
Classifier: License :: OSI Approved :: GNU General Public License v3 or later (GPLv3+)
Classifier: Programming Language :: Python :: 3
Classifier: Programming Language :: Python :: 3.9
Classifier: Programming Language :: Python :: 3.10
Requires-Dist: click (>=8.1.3,<9.0.0)
Requires-Dist: daiquiri (>=3.2.1,<4.0.0)
Requires-Dist: openpyxl (>=3.0.10,<4.0.0)
Requires-Dist: pandas (>=1.4.4,<2.0.0)
Requires-Dist: pydantic (>=1.10.2,<2.0.0)
Requires-Dist: requests (>=2.28.1,<3.0.0)
Requires-Dist: tabulate (>=0.8.10,<0.9.0)
Project-URL: Repository, https://github.com/userlerueda/utr
